setup.cfg
setup.py
sqlwhat_ext.py
sqlwhat_ext.egg-info/PKG-INFO
sqlwhat_ext.egg-info/SOURCES.txt
sqlwhat_ext.egg-info/dependency_links.txt
sqlwhat_ext.egg-info/requires.txt
sqlwhat_ext.egg-info/top_level.txt