Metadata-Version: 1.0
Name: sqlwhat-ext
Version: 0.0.1
Summary: sqlwhat extensions - high level SCTs
Home-page: https://github.com/datacamp/sqlwhat-ext
Author: Michael Chow
Author-email: michael@datacamp.com
License: UNKNOWN
Platform: UNKNOWN
